README.md
setup.py
MiD/__init__.py
MiD/active_contour_loss.py
MiD/data_augmentation.py
MiD/data_organizer.py
MiD/dataloads.py
MiD/deep_supervision_loss.py
MiD/get_information.py
MiD/get_nnunet_setting.py
MiD/inference.py
MiD/medical_decathlon_organizer.py
MiD/model.py
MiD/nnunet_3D_run.py
MiD/optimizer.py
MiD/patch_transform.py
MiD/preprocessing.py
MiD/sampling.py
MiD/trainer.py
MiD/transform.py
MiD/visualization.py
MiD.egg-info/PKG-INFO
MiD.egg-info/SOURCES.txt
MiD.egg-info/dependency_links.txt
MiD.egg-info/not-zip-safe
MiD.egg-info/requires.txt
MiD.egg-info/top_level.txt