Metadata-Version: 1.0
Name: MiD
Version: 0.1.2
Summary: Medical Deep Learning Framework.
Home-page: https://github.com/InGradient/InGradient_AI_Library
Author: seungyeob.seon
Author-email: liamseon@gmail.com
License: MIT
Keywords: pypi deploy
Platform: UNKNOWN
